{"document_id": "ae44803f-563f-4f39-8bb2-6619d508781b", "image": {"name": "10_2023_11_07_01_13_29_383435.jpg", "height": 640, "width": 640, "storage": {}}, "usecase": {"usecase_id": 6, "name": "Vehicle Detection", "incident": [{"incident_no": 0, "incident_id": 9, "name": "vehicle", "coordinate": {"x1": 95, "x2": 462, "y1": 147, "y2": 454}, "track_id": null, "misc": []}, {"incident_no": 1, "incident_id": 9, "name": "vehicle", "coordinate": {"x1": 528, "x2": 639, "y1": 196, "y2": 327}, "track_id": null, "misc": []}, {"incident_no": 2, "incident_id": 9, "name": "vehicle", "coordinate": {"x1": 447, "x2": 522, "y1": 185, "y2": 262}, "track_id": null, "misc": []}]}, "time": {"timestamp": 1699319609000, "zone": "", "incident_time": "2023-11-07 06:43:29.383435", "UTC_time": "2023-11-07 01:13:29.383435"}, "hierarchy": {"camera_id": 10, "camera_name": "ANPR", "subsite_id": 4, "subsite_name": "Floor 5", "location_id": 4, "location_name": "Office", "customer_id": 2, "customer_name": "Tata iQ", "zone_id": 4, "zone_name": "Pantry", "city_name": "Bangalore", "city_id": 4}, "pipeline_inform": {"preprocess_id": null, "schedule_id": "", "camera_group_id": 25, "model_meta": [], "computation_meta": []}, "prediction": [{"class": 2, "id": null, "class_name": "car", "score": 0.93, "xmin": 95, "ymin": 147, "xmax": 462, "ymax": 454, "xmin_c": 0.149, "ymin_c": 0.23123, "xmax_c": 0.72249, "ymax_c": 0.71066, "class_id": "6", "image_time": "2023-11-07 01:13:29.383435", "incident_status": true}, {"class": 5, "id": null, "class_name": "numberplate", "score": 0.85, "xmin": 211, "ymin": 367, "xmax": 329, "ymax": 398, "xmin_c": 0.33065, "ymin_c": 0.57434, "xmax_c": 0.51426, "ymax_c": 0.62216, "class_id": "12", "image_time": "2023-11-07 01:13:29.383435", "incident_status": false}, {"class": 5, "id": null, "class_name": "numberplate", "score": 0.68, "xmin": 477, "ymin": 247, "xmax": 492, "ymax": 257, "xmin_c": 0.74544, "ymin_c": 0.38662, "xmax_c": 0.76975, "ymax_c": 0.40264, "class_id": "12", "image_time": "2023-11-07 01:13:29.383435", "incident_status": false}, {"class": 4, "id": null, "class_name": "motorcycle", "score": 0.63, "xmin": 528, "ymin": 196, "xmax": 639, "ymax": 327, "xmin_c": 0.82578, "ymin_c": 0.30734, "xmax_c": 0.99971, "ymax_c": 0.51164, "class_id": "11", "image_time": "2023-11-07 01:13:29.383435", "incident_status": true}, {"class": 4, "id": null, "class_name": "motorcycle", "score": 0.54, "xmin": 447, "ymin": 185, "xmax": 522, "ymax": 262, "xmin_c": 0.69887, "ymin_c": 0.28989, "xmax_c": 0.8164, "ymax_c": 0.41071, "class_id": "11", "image_time": "2023-11-07 01:13:29.383435", "incident_status": true}, {"class": 5, "id": null, "class_name": "numberplate", "score": 0.22, "xmin": 611, "ymin": 308, "xmax": 628, "ymax": 328, "xmin_c": 0.9562, "ymin_c": 0.4823, "xmax_c": 0.98194, "ymax_c": 0.51272, "class_id": "12", "image_time": "2023-11-07 01:13:29.383435", "incident_status": false}], "incident_count": 3}