{"document_id": "28a08583-2b7a-495d-bda6-3244723885fd", "image": {"name": "10_2023_11_06_19_31_41_805889.jpg", "height": 640, "width": 640, "storage": {}}, "usecase": {"usecase_id": 6, "name": "Vehicle Detection", "incident": [{"incident_no": 0, "incident_id": 9, "name": "vehicle", "coordinate": {"x1": 221, "x2": 364, "y1": 273, "y2": 380}, "track_id": null, "misc": []}, {"incident_no": 1, "incident_id": 9, "name": "vehicle", "coordinate": {"x1": 542, "x2": 640, "y1": 304, "y2": 464}, "track_id": null, "misc": []}, {"incident_no": 2, "incident_id": 9, "name": "vehicle", "coordinate": {"x1": 453, "x2": 562, "y1": 292, "y2": 385}, "track_id": null, "misc": []}]}, "time": {"timestamp": 1699299101000, "zone": "", "incident_time": "2023-11-07 01:01:41.805889", "UTC_time": "2023-11-06 19:31:41.805889"}, "hierarchy": {"camera_id": 10, "camera_name": "ANPR", "subsite_id": 4, "subsite_name": "Floor 5", "location_id": 4, "location_name": "Office", "customer_id": 2, "customer_name": "Tata iQ", "zone_id": 4, "zone_name": "Pantry", "city_name": "Bangalore", "city_id": 4}, "pipeline_inform": {"preprocess_id": null, "schedule_id": "", "camera_group_id": 25, "model_meta": [], "computation_meta": []}, "prediction": [{"class": 2, "id": null, "class_name": "car", "score": 0.94, "xmin": 221, "ymin": 273, "xmax": 364, "ymax": 380, "xmin_c": 0.34625, "ymin_c": 0.42695, "xmax_c": 0.56991, "ymax_c": 0.59507, "class_id": "6", "image_time": "2023-11-06 19:31:41.805889", "incident_status": true}, {"class": 5, "id": null, "class_name": "numberplate", "score": 0.82, "xmin": 256, "ymin": 344, "xmax": 293, "ymax": 355, "xmin_c": 0.40141, "ymin_c": 0.53865, "xmax_c": 0.45838, "ymax_c": 0.55522, "class_id": "12", "image_time": "2023-11-06 19:31:41.805889", "incident_status": false}, {"class": 4, "id": null, "class_name": "motorcycle", "score": 0.79, "xmin": 542, "ymin": 304, "xmax": 640, "ymax": 464, "xmin_c": 0.84694, "ymin_c": 0.47542, "xmax_c": 1.0, "ymax_c": 0.7256, "class_id": "11", "image_time": "2023-11-06 19:31:41.805889", "incident_status": true}, {"class": 4, "id": null, "class_name": "motorcycle", "score": 0.77, "xmin": 453, "ymin": 292, "xmax": 562, "ymax": 385, "xmin_c": 0.70788, "ymin_c": 0.45754, "xmax_c": 0.87937, "ymax_c": 0.60184, "class_id": "11", "image_time": "2023-11-06 19:31:41.805889", "incident_status": true}, {"class": 5, "id": null, "class_name": "numberplate", "score": 0.18, "xmin": 554, "ymin": 372, "xmax": 570, "ymax": 389, "xmin_c": 0.86606, "ymin_c": 0.58267, "xmax_c": 0.89194, "ymax_c": 0.60932, "class_id": "12", "image_time": "2023-11-06 19:31:41.805889", "incident_status": false}], "incident_count": 3}