{"document_id": "26ffb9b2-7f33-491c-ba71-0a94298df09a", "image": {"name": "10_2023_11_04_04_11_08_800965.jpg", "height": 640, "width": 640, "storage": {}}, "usecase": {"usecase_id": 6, "name": "Vehicle Detection", "incident": [{"incident_no": 0, "incident_id": 9, "name": "vehicle", "coordinate": {"x1": 95, "x2": 463, "y1": 148, "y2": 452}, "track_id": null, "misc": []}, {"incident_no": 1, "incident_id": 9, "name": "vehicle", "coordinate": {"x1": 534, "x2": 639, "y1": 194, "y2": 326}, "track_id": null, "misc": []}, {"incident_no": 2, "incident_id": 9, "name": "vehicle", "coordinate": {"x1": 448, "x2": 525, "y1": 181, "y2": 262}, "track_id": null, "misc": []}]}, "time": {"timestamp": 1699071068000, "zone": "", "incident_time": "2023-11-04 04:11:08.800965", "UTC_time": "2023-11-04 04:11:08.800965"}, "hierarchy": {"camera_id": 10, "camera_name": "ANPR", "subsite_id": 4, "subsite_name": "Floor 5", "location_id": 4, "location_name": "Office", "customer_id": 2, "customer_name": "Tata iQ", "zone_id": 4, "zone_name": "Pantry", "city_name": "Bangalore", "city_id": 4}, "pipeline_inform": {"preprocess_id": null, "schedule_id": "", "camera_group_id": 25, "model_meta": [], "computation_meta": []}, "prediction": [{"class": 2, "id": null, "class_name": "car", "score": 0.93, "xmin": 95, "ymin": 148, "xmax": 463, "ymax": 452, "xmin_c": 0.14916, "ymin_c": 0.23204, "xmax_c": 0.72466, "ymax_c": 0.70774, "class_id": "6", "image_time": "2023-11-04 04:11:08.800965", "incident_status": true}, {"class": 5, "id": null, "class_name": "numberplate", "score": 0.85, "xmin": 213, "ymin": 368, "xmax": 330, "ymax": 398, "xmin_c": 0.33331, "ymin_c": 0.57595, "xmax_c": 0.51663, "ymax_c": 0.62231, "class_id": "12", "image_time": "2023-11-04 04:11:08.800965", "incident_status": false}, {"class": 4, "id": null, "class_name": "motorcycle", "score": 0.66, "xmin": 534, "ymin": 194, "xmax": 639, "ymax": 326, "xmin_c": 0.83549, "ymin_c": 0.30405, "xmax_c": 0.99941, "ymax_c": 0.50986, "class_id": "11", "image_time": "2023-11-04 04:11:08.800965", "incident_status": true}, {"class": 5, "id": null, "class_name": "numberplate", "score": 0.63, "xmin": 478, "ymin": 246, "xmax": 494, "ymax": 255, "xmin_c": 0.74807, "ymin_c": 0.38508, "xmax_c": 0.77338, "ymax_c": 0.39989, "class_id": "12", "image_time": "2023-11-04 04:11:08.800965", "incident_status": false}, {"class": 4, "id": null, "class_name": "motorcycle", "score": 0.58, "xmin": 448, "ymin": 181, "xmax": 525, "ymax": 262, "xmin_c": 0.70054, "ymin_c": 0.28369, "xmax_c": 0.82128, "ymax_c": 0.41042, "class_id": "11", "image_time": "2023-11-04 04:11:08.800965", "incident_status": true}, {"class": 5, "id": null, "class_name": "numberplate", "score": 0.15, "xmin": 613, "ymin": 306, "xmax": 631, "ymax": 326, "xmin_c": 0.95911, "ymin_c": 0.4793, "xmax_c": 0.98599, "ymax_c": 0.51057, "class_id": "12", "image_time": "2023-11-04 04:11:08.800965", "incident_status": false}], "incident_count": 3}