{"document_id": "67e1dd23-3c6c-4233-b9fb-0bb657311442", "image": {"name": "10_2023_11_06_13_27_54_552949.jpg", "height": 640, "width": 640, "storage": {}}, "usecase": {"usecase_id": 6, "name": "Vehicle Detection", "incident": [{"incident_no": 0, "incident_id": 9, "name": "vehicle", "coordinate": {"x1": 227, "x2": 369, "y1": 274, "y2": 381}, "track_id": null, "misc": []}, {"incident_no": 1, "incident_id": 9, "name": "vehicle", "coordinate": {"x1": 552, "x2": 640, "y1": 300, "y2": 465}, "track_id": null, "misc": []}, {"incident_no": 2, "incident_id": 9, "name": "vehicle", "coordinate": {"x1": 457, "x2": 562, "y1": 291, "y2": 385}, "track_id": null, "misc": []}]}, "time": {"timestamp": 1699277274000, "zone": "", "incident_time": "2023-11-06 18:57:54.552949", "UTC_time": "2023-11-06 13:27:54.552949"}, "hierarchy": {"camera_id": 10, "camera_name": "ANPR", "subsite_id": 4, "subsite_name": "Floor 5", "location_id": 4, "location_name": "Office", "customer_id": 2, "customer_name": "Tata iQ", "zone_id": 4, "zone_name": "Pantry", "city_name": "Bangalore", "city_id": 4}, "pipeline_inform": {"preprocess_id": null, "schedule_id": "", "camera_group_id": 25, "model_meta": [], "computation_meta": []}, "prediction": [{"class": 2, "id": null, "class_name": "car", "score": 0.95, "xmin": 227, "ymin": 274, "xmax": 369, "ymax": 381, "xmin_c": 0.35595, "ymin_c": 0.42824, "xmax_c": 0.57688, "ymax_c": 0.59685, "class_id": "6", "image_time": "2023-11-06 13:27:54.552949", "incident_status": true}, {"class": 5, "id": null, "class_name": "numberplate", "score": 0.82, "xmin": 262, "ymin": 345, "xmax": 298, "ymax": 355, "xmin_c": 0.40959, "ymin_c": 0.5405, "xmax_c": 0.46702, "ymax_c": 0.55607, "class_id": "12", "image_time": "2023-11-06 13:27:54.552949", "incident_status": false}, {"class": 4, "id": null, "class_name": "motorcycle", "score": 0.79, "xmin": 552, "ymin": 300, "xmax": 640, "ymax": 465, "xmin_c": 0.8626, "ymin_c": 0.46976, "xmax_c": 1.0, "ymax_c": 0.72785, "class_id": "11", "image_time": "2023-11-06 13:27:54.552949", "incident_status": true}, {"class": 4, "id": null, "class_name": "motorcycle", "score": 0.74, "xmin": 457, "ymin": 291, "xmax": 562, "ymax": 385, "xmin_c": 0.71459, "ymin_c": 0.45581, "xmax_c": 0.87912, "ymax_c": 0.60237, "class_id": "11", "image_time": "2023-11-06 13:27:54.552949", "incident_status": true}, {"class": 5, "id": null, "class_name": "numberplate", "score": 0.1, "xmin": 560, "ymin": 372, "xmax": 577, "ymax": 390, "xmin_c": 0.87517, "ymin_c": 0.58199, "xmax_c": 0.90207, "ymax_c": 0.61026, "class_id": "12", "image_time": "2023-11-06 13:27:54.552949", "incident_status": false}], "incident_count": 3}