{"document_id": "d562bafc-cb22-45e0-8919-59cef4075c73", "image": {"name": "10_2023_11_06_21_22_13_718213.jpg", "height": 640, "width": 640, "storage": {}}, "usecase": {"usecase_id": 6, "name": "Vehicle Detection", "incident": [{"incident_no": 0, "incident_id": 9, "name": "vehicle", "coordinate": {"x1": 221, "x2": 365, "y1": 272, "y2": 380}, "track_id": null, "misc": []}, {"incident_no": 1, "incident_id": 9, "name": "vehicle", "coordinate": {"x1": 543, "x2": 640, "y1": 303, "y2": 462}, "track_id": null, "misc": []}, {"incident_no": 2, "incident_id": 9, "name": "vehicle", "coordinate": {"x1": 453, "x2": 561, "y1": 290, "y2": 384}, "track_id": null, "misc": []}]}, "time": {"timestamp": 1699305733000, "zone": "", "incident_time": "2023-11-07 02:52:13.718213", "UTC_time": "2023-11-06 21:22:13.718213"}, "hierarchy": {"camera_id": 10, "camera_name": "ANPR", "subsite_id": 4, "subsite_name": "Floor 5", "location_id": 4, "location_name": "Office", "customer_id": 2, "customer_name": "Tata iQ", "zone_id": 4, "zone_name": "Pantry", "city_name": "Bangalore", "city_id": 4}, "pipeline_inform": {"preprocess_id": null, "schedule_id": "", "camera_group_id": 25, "model_meta": [], "computation_meta": []}, "prediction": [{"class": 2, "id": null, "class_name": "car", "score": 0.95, "xmin": 221, "ymin": 272, "xmax": 365, "ymax": 380, "xmin_c": 0.34661, "ymin_c": 0.42536, "xmax_c": 0.57044, "ymax_c": 0.59439, "class_id": "6", "image_time": "2023-11-06 21:22:13.718213", "incident_status": true}, {"class": 5, "id": null, "class_name": "numberplate", "score": 0.84, "xmin": 257, "ymin": 344, "xmax": 293, "ymax": 355, "xmin_c": 0.40164, "ymin_c": 0.53801, "xmax_c": 0.45918, "ymax_c": 0.55486, "class_id": "12", "image_time": "2023-11-06 21:22:13.718213", "incident_status": false}, {"class": 4, "id": null, "class_name": "motorcycle", "score": 0.79, "xmin": 543, "ymin": 303, "xmax": 640, "ymax": 462, "xmin_c": 0.84896, "ymin_c": 0.47498, "xmax_c": 1.0, "ymax_c": 0.72316, "class_id": "11", "image_time": "2023-11-06 21:22:13.718213", "incident_status": true}, {"class": 4, "id": null, "class_name": "motorcycle", "score": 0.79, "xmin": 453, "ymin": 290, "xmax": 561, "ymax": 384, "xmin_c": 0.70837, "ymin_c": 0.45433, "xmax_c": 0.87693, "ymax_c": 0.60095, "class_id": "11", "image_time": "2023-11-06 21:22:13.718213", "incident_status": true}, {"class": 5, "id": null, "class_name": "numberplate", "score": 0.2, "xmin": 531, "ymin": 370, "xmax": 551, "ymax": 381, "xmin_c": 0.83032, "ymin_c": 0.57828, "xmax_c": 0.86114, "ymax_c": 0.5968, "class_id": "12", "image_time": "2023-11-06 21:22:13.718213", "incident_status": false}, {"class": 5, "id": null, "class_name": "numberplate", "score": 0.18, "xmin": 555, "ymin": 372, "xmax": 571, "ymax": 388, "xmin_c": 0.86762, "ymin_c": 0.5815, "xmax_c": 0.89226, "ymax_c": 0.6077, "class_id": "12", "image_time": "2023-11-06 21:22:13.718213", "incident_status": false}], "incident_count": 3}