{"document_id": "246c8531-a2ec-480c-b842-d741df25d7e3", "image": {"name": "11_2023_11_04_01_45_55_319665.jpg", "height": 360, "width": 640, "storage": {}}, "usecase": {"usecase_id": 10, "name": "fire smoke", "incident": [{"incident_no": 0, "incident_id": 7, "name": "fire smoke", "coordinate": {"x1": 2, "x2": 97, "y1": 55, "y2": 353}, "track_id": null, "misc": []}, {"incident_no": 1, "incident_id": 7, "name": "fire smoke", "coordinate": {"x1": 357, "x2": 430, "y1": 7, "y2": 133}, "track_id": null, "misc": []}]}, "time": {"timestamp": 1699062355000, "zone": "", "incident_time": "2023-11-04 01:45:55.319665", "UTC_time": "2023-11-04 01:45:55.319665"}, "hierarchy": {"camera_id": 11, "camera_name": "Fire Smoke", "subsite_id": 4, "subsite_name": "Floor 5", "location_id": 4, "location_name": "Office", "customer_id": 2, "customer_name": "Tata iQ", "zone_id": 4, "zone_name": "Pantry", "city_name": "Bangalore", "city_id": 4}, "pipeline_inform": {"preprocess_id": 3, "schedule_id": "", "camera_group_id": 26, "model_meta": [], "computation_meta": []}, "prediction": [{"class": 1, "id": null, "class_name": "smoke", "score": 0.51, "xmin": 2, "ymin": 55, "xmax": 97, "ymax": 353, "xmin_c": 0.00339, "ymin_c": 0.15536, "xmax_c": 0.15185, "ymax_c": 0.98074, "class_id": "16", "image_time": "2023-11-04 01:45:55.319665", "incident_status": true}, {"class": 0, "id": null, "class_name": "fire", "score": 0.49, "xmin": 357, "ymin": 7, "xmax": 430, "ymax": 133, "xmin_c": 0.55893, "ymin_c": 0.0203, "xmax_c": 0.67287, "ymax_c": 0.37061, "class_id": "15", "image_time": "2023-11-04 01:45:55.319665", "incident_status": true}], "incident_count": 2}