{"document_id": "93a02542-b005-41bb-95f7-0f05e62fdac6", "image": {"name": "11_2023_11_03_18_02_14_862507.jpg", "height": 360, "width": 640, "storage": {}}, "usecase": {"usecase_id": 10, "name": "fire smoke", "incident": [{"incident_no": 0, "incident_id": 7, "name": "fire smoke", "coordinate": {"x1": 0, "x2": 33, "y1": 34, "y2": 263}, "track_id": null, "misc": []}]}, "time": {"timestamp": 1699034534000, "zone": "", "incident_time": "2023-11-03 18:02:14.862507", "UTC_time": "2023-11-03 18:02:14.862507"}, "hierarchy": {"camera_id": 11, "camera_name": "Fire Smoke", "subsite_id": 4, "subsite_name": "Floor 5", "location_id": 4, "location_name": "Office", "customer_id": 2, "customer_name": "Tata iQ", "zone_id": 4, "zone_name": "Pantry", "city_name": "Bangalore", "city_id": 4}, "pipeline_inform": {"preprocess_id": 3, "schedule_id": "", "camera_group_id": 26, "model_meta": [], "computation_meta": []}, "prediction": [{"class": 1, "id": null, "class_name": "smoke", "score": 0.4, "xmin": 0, "ymin": 34, "xmax": 33, "ymax": 263, "xmin_c": 0.0, "ymin_c": 0.09674, "xmax_c": 0.05161, "ymax_c": 0.73209, "class_id": "16", "image_time": "2023-11-03 18:02:14.862507", "incident_status": true}], "incident_count": 1}