{"document_id": "a881cd53-e172-4f9d-907e-fd44f695b73a", "image": {"name": "11_2023_11_06_16_04_46_639899.jpg", "height": 360, "width": 640, "storage": {}}, "usecase": {"usecase_id": 10, "name": "fire smoke", "incident": [{"incident_no": 0, "incident_id": 7, "name": "fire smoke", "coordinate": {"x1": 333, "x2": 442, "y1": 1, "y2": 115}, "track_id": null, "misc": []}]}, "time": {"timestamp": 1699286686000, "zone": "", "incident_time": "2023-11-06 21:34:46.639899", "UTC_time": "2023-11-06 16:04:46.639899"}, "hierarchy": {"camera_id": 11, "camera_name": "Fire Smoke", "subsite_id": 4, "subsite_name": "Floor 5", "location_id": 4, "location_name": "Office", "customer_id": 2, "customer_name": "Tata iQ", "zone_id": 4, "zone_name": "Pantry", "city_name": "Bangalore", "city_id": 4}, "pipeline_inform": {"preprocess_id": 3, "schedule_id": "", "camera_group_id": 26, "model_meta": [], "computation_meta": []}, "prediction": [{"class": 0, "id": null, "class_name": "fire", "score": 0.35, "xmin": 333, "ymin": 1, "xmax": 442, "ymax": 115, "xmin_c": 0.52126, "ymin_c": 0.00405, "xmax_c": 0.69096, "ymax_c": 0.32096, "class_id": "15", "image_time": "2023-11-06 16:04:46.639899", "incident_status": true}], "incident_count": 1}