{"document_id": "05dcb30a-92fe-43f7-b6bf-de7b2f6d89d7", "image": {"name": "11_2023_11_06_12_25_17_651220.jpg", "height": 360, "width": 640, "storage": {}}, "usecase": {"usecase_id": 10, "name": "fire smoke", "incident": [{"incident_no": 0, "incident_id": 7, "name": "fire smoke", "coordinate": {"x1": 0, "x2": 30, "y1": 13, "y2": 263}, "track_id": null, "misc": []}, {"incident_no": 1, "incident_id": 7, "name": "fire smoke", "coordinate": {"x1": 39, "x2": 283, "y1": 42, "y2": 323}, "track_id": null, "misc": []}]}, "time": {"timestamp": 1699273517000, "zone": "", "incident_time": "2023-11-06 17:55:17.651220", "UTC_time": "2023-11-06 12:25:17.651220"}, "hierarchy": {"camera_id": 11, "camera_name": "Fire Smoke", "subsite_id": 4, "subsite_name": "Floor 5", "location_id": 4, "location_name": "Office", "customer_id": 2, "customer_name": "Tata iQ", "zone_id": 4, "zone_name": "Pantry", "city_name": "Bangalore", "city_id": 4}, "pipeline_inform": {"preprocess_id": 3, "schedule_id": "", "camera_group_id": 26, "model_meta": [], "computation_meta": []}, "prediction": [{"class": 1, "id": null, "class_name": "smoke", "score": 0.7, "xmin": 0, "ymin": 13, "xmax": 30, "ymax": 263, "xmin_c": 0.0, "ymin_c": 0.03772, "xmax_c": 0.04754, "ymax_c": 0.73102, "class_id": "16", "image_time": "2023-11-06 12:25:17.651220", "incident_status": true}, {"class": 1, "id": null, "class_name": "smoke", "score": 0.36, "xmin": 39, "ymin": 42, "xmax": 283, "ymax": 323, "xmin_c": 0.06124, "ymin_c": 0.11897, "xmax_c": 0.44304, "ymax_c": 0.89918, "class_id": "16", "image_time": "2023-11-06 12:25:17.651220", "incident_status": true}], "incident_count": 2}