{"document_id": "2c9e5e1b-ef37-439c-8ffd-36bf5cf5ee37", "image": {"name": "11_2023_11_03_10_52_18_579881.jpg", "height": 360, "width": 640, "storage": {}}, "usecase": {"usecase_id": 10, "name": "fire smoke", "incident": [{"incident_no": 0, "incident_id": 7, "name": "fire smoke", "coordinate": {"x1": 334, "x2": 446, "y1": 1, "y2": 115}, "track_id": null, "misc": []}, {"incident_no": 1, "incident_id": 7, "name": "fire smoke", "coordinate": {"x1": 120, "x2": 295, "y1": 53, "y2": 314}, "track_id": null, "misc": []}, {"incident_no": 2, "incident_id": 7, "name": "fire smoke", "coordinate": {"x1": 344, "x2": 403, "y1": 117, "y2": 148}, "track_id": null, "misc": []}]}, "time": {"timestamp": 1699008738000, "zone": "", "incident_time": "2023-11-03 10:52:18.579881", "UTC_time": "2023-11-03 10:52:18.579881"}, "hierarchy": {"camera_id": 11, "camera_name": "Fire Smoke", "subsite_id": 4, "subsite_name": "Floor 5", "location_id": 4, "location_name": "Office", "customer_id": 2, "customer_name": "Tata iQ", "zone_id": 4, "zone_name": "Pantry", "city_name": "Bangalore", "city_id": 4}, "pipeline_inform": {"preprocess_id": 3, "schedule_id": "", "camera_group_id": 26, "model_meta": [], "computation_meta": []}, "prediction": [{"class": 0, "id": null, "class_name": "fire", "score": 0.38, "xmin": 334, "ymin": 1, "xmax": 446, "ymax": 115, "xmin_c": 0.52231, "ymin_c": 0.00433, "xmax_c": 0.69776, "ymax_c": 0.32072, "class_id": "15", "image_time": "2023-11-03 10:52:18.579881", "incident_status": true}, {"class": 1, "id": null, "class_name": "smoke", "score": 0.3, "xmin": 120, "ymin": 53, "xmax": 295, "ymax": 314, "xmin_c": 0.188, "ymin_c": 0.14742, "xmax_c": 0.46124, "ymax_c": 0.87317, "class_id": "16", "image_time": "2023-11-03 10:52:18.579881", "incident_status": true}, {"class": 0, "id": null, "class_name": "fire", "score": 0.23, "xmin": 344, "ymin": 117, "xmax": 403, "ymax": 148, "xmin_c": 0.53826, "ymin_c": 0.32521, "xmax_c": 0.6299, "ymax_c": 0.41283, "class_id": "15", "image_time": "2023-11-03 10:52:18.579881", "incident_status": true}], "incident_count": 3}