{"document_id": "3b6d31df-30a8-42f1-99b1-6e2339933ecf", "image": {"name": "4_2023_11_01_03_06_17_085881.jpg", "height": 360, "width": 640, "storage": {}}, "usecase": {"usecase_id": 4, "name": "Crowd Usecase", "incident": [{"incident_no": 0, "incident_id": 3, "name": "Crowd", "track_id": null, "coordinate": {"x1": "", "x2": "", "y1": "", "y2": ""}, "misc": [{"data": 3, "text": "human"}]}]}, "time": {"timestamp": 1698807977000, "zone": "", "incident_time": "2023-11-01 03:06:17.085881", "UTC_time": "2023-11-01 03:06:17.085881"}, "hierarchy": {"camera_id": 4, "camera_name": "CAM_PANTRY_01", "subsite_id": 4, "subsite_name": "Floor 5", "location_id": 4, "location_name": "Office", "customer_id": 2, "customer_name": "Tata iQ", "zone_id": 4, "zone_name": "Pantry", "city_name": "Bangalore", "city_id": 4}, "pipeline_inform": {"preprocess_id": null, "schedule_id": "", "camera_group_id": 17, "model_meta": [], "computation_meta": []}, "prediction": [{"class": 0, "id": 3, "class_name": "human", "score": 0.88, "xmin": 219, "ymin": 154, "xmax": 288, "ymax": 302, "xmin_c": 0.34339, "ymin_c": 0.4288, "xmax_c": 0.45137, "ymax_c": 0.83947, "class_id": "1", "image_time": "2023-11-01 03:06:17.085881", "incident_status": false}, {"class": 0, "id": 6, "class_name": "human", "score": 0.84, "xmin": 356, "ymin": 134, "xmax": 397, "ymax": 262, "xmin_c": 0.55657, "ymin_c": 0.37316, "xmax_c": 0.62129, "ymax_c": 0.72814, "class_id": "1", "image_time": "2023-11-01 03:06:17.085881", "incident_status": false}, {"class": 0, "id": 84, "class_name": "human", "score": 0.23, "xmin": 592, "ymin": 83, "xmax": 639, "ymax": 357, "xmin_c": 0.92647, "ymin_c": 0.23276, "xmax_c": 0.99999, "ymax_c": 0.99277, "class_id": "1", "image_time": "2023-11-01 03:06:17.085881", "incident_status": false}], "incident_count": 1}