{"document_id": "2b434ebb-71e3-413a-9e90-178d4ad525cc", "image": {"name": "4_2023_11_01_05_11_16_863897.jpg", "height": 360, "width": 640, "storage": {}}, "usecase": {"usecase_id": 4, "name": "Crowd Usecase", "incident": [{"incident_no": 0, "incident_id": 3, "name": "Crowd", "track_id": null, "coordinate": {"x1": "", "x2": "", "y1": "", "y2": ""}, "misc": [{"data": 4, "text": "human"}]}]}, "time": {"timestamp": 1698815476000, "zone": "", "incident_time": "2023-11-01 05:11:16.863897", "UTC_time": "2023-11-01 05:11:16.863897"}, "hierarchy": {"camera_id": 4, "camera_name": "CAM_PANTRY_01", "subsite_id": 4, "subsite_name": "Floor 5", "location_id": 4, "location_name": "Office", "customer_id": 2, "customer_name": "Tata iQ", "zone_id": 4, "zone_name": "Pantry", "city_name": "Bangalore", "city_id": 4}, "pipeline_inform": {"preprocess_id": null, "schedule_id": "", "camera_group_id": 17, "model_meta": [], "computation_meta": []}, "prediction": [{"class": 0, "id": null, "class_name": "human", "score": 0.82, "xmin": 225, "ymin": 111, "xmax": 260, "ymax": 195, "xmin_c": 0.35291, "ymin_c": 0.31007, "xmax_c": 0.40628, "ymax_c": 0.54186, "class_id": "1", "image_time": "2023-11-01 05:11:16.863897", "incident_status": false}, {"class": 0, "id": null, "class_name": "human", "score": 0.7, "xmin": 271, "ymin": 76, "xmax": 290, "ymax": 136, "xmin_c": 0.42399, "ymin_c": 0.21338, "xmax_c": 0.4532, "ymax_c": 0.37815, "class_id": "1", "image_time": "2023-11-01 05:11:16.863897", "incident_status": false}, {"class": 0, "id": null, "class_name": "human", "score": 0.21, "xmin": 428, "ymin": 98, "xmax": 456, "ymax": 132, "xmin_c": 0.66922, "ymin_c": 0.27238, "xmax_c": 0.71277, "ymax_c": 0.36854, "class_id": "1", "image_time": "2023-11-01 05:11:16.863897", "incident_status": false}, {"class": 0, "id": null, "class_name": "human", "score": 0.1, "xmin": 593, "ymin": 72, "xmax": 639, "ymax": 357, "xmin_c": 0.9272, "ymin_c": 0.20026, "xmax_c": 0.99999, "ymax_c": 0.99211, "class_id": "1", "image_time": "2023-11-01 05:11:16.863897", "incident_status": false}], "incident_count": 1}