{"document_id": "73364063-a745-4679-b94b-6ceebf9b7d00", "image": {"name": "5_2023_11_03_17_02_32_002008.jpg", "height": 360, "width": 640, "storage": {}}, "usecase": {"usecase_id": 5, "name": "Garbage", "incident": [{"incident_no": 0, "incident_id": 5, "name": "Garbages", "coordinate": {"x1": 297, "x2": 321, "y1": 231, "y2": 249}, "track_id": null, "misc": []}, {"incident_no": 1, "incident_id": 5, "name": "Garbages", "coordinate": {"x1": 416, "x2": 439, "y1": 223, "y2": 282}, "track_id": null, "misc": []}]}, "time": {"timestamp": 1699030952000, "zone": "", "incident_time": "2023-11-03 17:02:32.002008", "UTC_time": "2023-11-03 17:02:32.002008"}, "hierarchy": {"camera_id": 5, "camera_name": "CAM_04", "subsite_id": 4, "subsite_name": "Floor 5", "location_id": 4, "location_name": "Office", "customer_id": 2, "customer_name": "Tata iQ", "zone_id": 4, "zone_name": "Pantry", "city_name": "Bangalore", "city_id": 4}, "pipeline_inform": {"preprocess_id": null, "schedule_id": "", "camera_group_id": 18, "model_meta": [], "computation_meta": []}, "prediction": [{"class": 0, "id": null, "class_name": "garbage", "score": 0.64, "xmin": 297, "ymin": 231, "xmax": 321, "ymax": 249, "xmin_c": 0.46495, "ymin_c": 0.64282, "xmax_c": 0.50259, "ymax_c": 0.69232, "class_id": "13", "image_time": "2023-11-03 17:02:32.002008", "incident_status": true}, {"class": 0, "id": null, "class_name": "garbage", "score": 0.13, "xmin": 416, "ymin": 223, "xmax": 439, "ymax": 282, "xmin_c": 0.65013, "ymin_c": 0.62035, "xmax_c": 0.68694, "ymax_c": 0.78446, "class_id": "13", "image_time": "2023-11-03 17:02:32.002008", "incident_status": true}], "incident_count": 2}