{"document_id": "9a9dcab5-8193-4745-be9c-f9b46d5fefe4", "image": {"name": "5_2023_11_06_16_36_36_611897.jpg", "height": 360, "width": 640, "storage": {}}, "usecase": {"usecase_id": 5, "name": "Garbage", "incident": [{"incident_no": 0, "incident_id": 5, "name": "Garbages", "coordinate": {"x1": 298, "x2": 321, "y1": 232, "y2": 249}, "track_id": null, "misc": []}, {"incident_no": 1, "incident_id": 5, "name": "Garbages", "coordinate": {"x1": 415, "x2": 440, "y1": 223, "y2": 282}, "track_id": null, "misc": []}]}, "time": {"timestamp": 1699288596000, "zone": "", "incident_time": "2023-11-06 22:06:36.611897", "UTC_time": "2023-11-06 16:36:36.611897"}, "hierarchy": {"camera_id": 5, "camera_name": "CAM_04", "subsite_id": 4, "subsite_name": "Floor 5", "location_id": 4, "location_name": "Office", "customer_id": 2, "customer_name": "Tata iQ", "zone_id": 4, "zone_name": "Pantry", "city_name": "Bangalore", "city_id": 4}, "pipeline_inform": {"preprocess_id": null, "schedule_id": "", "camera_group_id": 18, "model_meta": [], "computation_meta": []}, "prediction": [{"class": 0, "id": null, "class_name": "garbage", "score": 0.4, "xmin": 298, "ymin": 232, "xmax": 321, "ymax": 249, "xmin_c": 0.46647, "ymin_c": 0.64606, "xmax_c": 0.50241, "ymax_c": 0.69343, "class_id": "13", "image_time": "2023-11-06 16:36:36.611897", "incident_status": true}, {"class": 0, "id": null, "class_name": "garbage", "score": 0.15, "xmin": 415, "ymin": 223, "xmax": 440, "ymax": 282, "xmin_c": 0.64953, "ymin_c": 0.62086, "xmax_c": 0.6882, "ymax_c": 0.78555, "class_id": "13", "image_time": "2023-11-06 16:36:36.611897", "incident_status": true}], "incident_count": 2}