{"document_id": "afe8b850-fd1a-4689-a5db-718daefe1495", "image": {"name": "8_2023_11_02_12_11_30_730201.jpg", "height": 480, "width": 640, "storage": {}}, "usecase": {"usecase_id": 12, "name": "PPE Test1", "incident": [{"incident_no": 0, "incident_id": 1, "name": "PPE Incident", "coordinate": {"x1": 292, "x2": 358, "y1": 395, "y2": 457}, "track_id": 361, "misc": []}, {"incident_no": 1, "incident_id": 1, "name": "PPE Incident", "coordinate": {"x1": 257, "x2": 368, "y1": 447, "y2": 479}, "track_id": 466, "misc": []}, {"incident_no": 2, "incident_id": 1, "name": "PPE Incident", "coordinate": {"x1": 249, "x2": 394, "y1": 390, "y2": 479}, "track_id": 505, "misc": []}]}, "time": {"timestamp": 1698927090000, "zone": "", "incident_time": "2023-11-02 12:11:30.730201", "UTC_time": "2023-11-02 12:11:30.730201"}, "hierarchy": {"camera_id": 8, "camera_name": "Warehous3", "subsite_id": 4, "subsite_name": "Floor 5", "location_id": 4, "location_name": "Office", "customer_id": 2, "customer_name": "Tata iQ", "zone_id": 4, "zone_name": "Pantry", "city_name": "Bangalore", "city_id": 4}, "pipeline_inform": {"preprocess_id": null, "schedule_id": "", "camera_group_id": 21, "model_meta": [], "computation_meta": []}, "prediction": [{"class": 2, "id": 361, "class_name": "nohelmet", "score": 0.88, "xmin": 292, "ymin": 395, "xmax": 358, "ymax": 457, "xmin_c": 0.45635, "ymin_c": 0.82399, "xmax_c": 0.56066, "ymax_c": 0.95329, "class_id": "2", "image_time": "2023-11-02 12:11:30.730201", "incident_status": true}, {"class": 4, "id": 466, "class_name": "novest", "score": 0.76, "xmin": 257, "ymin": 447, "xmax": 368, "ymax": 479, "xmin_c": 0.40269, "ymin_c": 0.93138, "xmax_c": 0.57544, "ymax_c": 1.0, "class_id": "3", "image_time": "2023-11-02 12:11:30.730201", "incident_status": true}, {"class": 0, "id": 505, "class_name": "human", "score": 0.72, "xmin": 249, "ymin": 390, "xmax": 394, "ymax": 479, "xmin_c": 0.38939, "ymin_c": 0.81296, "xmax_c": 0.61614, "ymax_c": 0.99956, "class_id": "1", "image_time": "2023-11-02 12:11:30.730201", "incident_status": true}, {"class": 5, "id": 525, "class_name": "face", "score": 0.64, "xmin": 306, "ymin": 433, "xmax": 355, "ymax": 463, "xmin_c": 0.47894, "ymin_c": 0.90255, "xmax_c": 0.55587, "ymax_c": 0.96537, "class_id": "18", "image_time": "2023-11-02 12:11:30.730201", "incident_status": false}], "incident_count": 3}