{"document_id": "34844dbf-61db-4065-b02e-3294e04f0d82", "image": {"name": "8_2023_11_02_11_26_09_515774.jpg", "height": 480, "width": 640, "storage": {}}, "usecase": {"usecase_id": 12, "name": "PPE Test1", "incident": [{"incident_no": 0, "incident_id": 1, "name": "PPE Incident", "coordinate": {"x1": 333, "x2": 443, "y1": 341, "y2": 480}, "track_id": 187, "misc": []}, {"incident_no": 1, "incident_id": 1, "name": "PPE Incident", "coordinate": {"x1": 341, "x2": 410, "y1": 372, "y2": 480}, "track_id": 269, "misc": []}, {"incident_no": 2, "incident_id": 1, "name": "PPE Incident", "coordinate": {"x1": 383, "x2": 441, "y1": 346, "y2": 411}, "track_id": 276, "misc": []}]}, "time": {"timestamp": 1698924369000, "zone": "", "incident_time": "2023-11-02 11:26:09.515774", "UTC_time": "2023-11-02 11:26:09.515774"}, "hierarchy": {"camera_id": 8, "camera_name": "Warehous3", "subsite_id": 4, "subsite_name": "Floor 5", "location_id": 4, "location_name": "Office", "customer_id": 2, "customer_name": "Tata iQ", "zone_id": 4, "zone_name": "Pantry", "city_name": "Bangalore", "city_id": 4}, "pipeline_inform": {"preprocess_id": null, "schedule_id": "", "camera_group_id": 21, "model_meta": [], "computation_meta": []}, "prediction": [{"class": 0, "id": 187, "class_name": "human", "score": 0.95, "xmin": 333, "ymin": 341, "xmax": 443, "ymax": 480, "xmin_c": 0.52092, "ymin_c": 0.71164, "xmax_c": 0.69259, "ymax_c": 1.0, "class_id": "1", "image_time": "2023-11-02 11:26:09.515774", "incident_status": true}, {"class": 4, "id": 269, "class_name": "novest", "score": 0.84, "xmin": 341, "ymin": 372, "xmax": 410, "ymax": 480, "xmin_c": 0.53407, "ymin_c": 0.77671, "xmax_c": 0.64127, "ymax_c": 1.0, "class_id": "3", "image_time": "2023-11-02 11:26:09.515774", "incident_status": true}, {"class": 2, "id": 276, "class_name": "nohelmet", "score": 0.61, "xmin": 383, "ymin": 346, "xmax": 441, "ymax": 411, "xmin_c": 0.59921, "ymin_c": 0.72217, "xmax_c": 0.68935, "ymax_c": 0.85732, "class_id": "2", "image_time": "2023-11-02 11:26:09.515774", "incident_status": true}, {"class": 8, "id": 279, "class_name": "arm", "score": 0.51, "xmin": 357, "ymin": 399, "xmax": 407, "ymax": 479, "xmin_c": 0.55806, "ymin_c": 0.83328, "xmax_c": 0.63712, "ymax_c": 0.99958, "class_id": "21", "image_time": "2023-11-02 11:26:09.515774", "incident_status": false}, {"class": 5, "id": 286, "class_name": "face", "score": 0.48, "xmin": 407, "ymin": 368, "xmax": 440, "ymax": 410, "xmin_c": 0.6365, "ymin_c": 0.76784, "xmax_c": 0.68757, "ymax_c": 0.85438, "class_id": "18", "image_time": "2023-11-02 11:26:09.515774", "incident_status": false}], "incident_count": 3}