{"document_id": "dd8487f7-19bf-4ae5-bb4b-9225d557a33b", "image": {"name": "12_2023_11_07_02_09_09_338892.jpg", "height": 360, "width": 640, "storage": {}}, "usecase": {"usecase_id": 15, "name": "intrusion incident", "incident": [{"incident_no": 0, "incident_id": 8, "name": "intrusion", "coordinate": {"x1": 592, "x2": 639, "y1": 125, "y2": 357}, "track_id": null, "misc": []}]}, "time": {"timestamp": 1699322949000, "zone": "", "incident_time": "2023-11-07 07:39:09.338892", "UTC_time": "2023-11-07 02:09:09.338892"}, "hierarchy": {"camera_id": 12, "camera_name": "intrusion", "subsite_id": 4, "subsite_name": "Floor 5", "location_id": 4, "location_name": "Office", "customer_id": 2, "customer_name": "Tata iQ", "zone_id": 4, "zone_name": "Pantry", "city_name": "Bangalore", "city_id": 4}, "pipeline_inform": {"preprocess_id": null, "schedule_id": "", "camera_group_id": 30, "model_meta": [], "computation_meta": []}, "prediction": [{"class": 0, "id": null, "class_name": "human", "score": 0.23, "xmin": 592, "ymin": 125, "xmax": 639, "ymax": 357, "xmin_c": 0.9261, "ymin_c": 0.34861, "xmax_c": 0.99993, "ymax_c": 0.9919, "class_id": "1", "image_time": "2023-11-07 02:09:09.338892", "incident_status": true, "human": 181.31}], "incident_count": 1}