{"document_id": "acdbdcd4-17f7-487c-ae7d-e4d51e6a1505", "image": {"name": "12_2023_11_01_03_24_00_643918.jpg", "height": 360, "width": 640, "storage": {}}, "usecase": {"usecase_id": 15, "name": "intrusion incident", "incident": [{"incident_no": 0, "incident_id": 8, "name": "intrusion", "coordinate": {"x1": 510, "x2": 569, "y1": 191, "y2": 347}, "track_id": 2, "misc": []}]}, "time": {"timestamp": 1698809040000, "zone": "", "incident_time": "2023-11-01 03:24:00.643918", "UTC_time": "2023-11-01 03:24:00.643918"}, "hierarchy": {"camera_id": 12, "camera_name": "intrusion", "subsite_id": 4, "subsite_name": "Floor 5", "location_id": 4, "location_name": "Office", "customer_id": 2, "customer_name": "Tata iQ", "zone_id": 4, "zone_name": "Pantry", "city_name": "Bangalore", "city_id": 4}, "pipeline_inform": {"preprocess_id": null, "schedule_id": "", "camera_group_id": 30, "model_meta": [], "computation_meta": []}, "prediction": [{"class": 0, "id": 2, "class_name": "human", "score": 0.85, "xmin": 510, "ymin": 191, "xmax": 569, "ymax": 347, "xmin_c": 0.79707, "ymin_c": 0.53312, "xmax_c": 0.88973, "ymax_c": 0.96609, "class_id": "1", "image_time": "2023-11-01 03:24:00.643918", "incident_status": true, "human": 0.0}, {"class": 0, "id": 12, "class_name": "human", "score": 0.36, "xmin": 592, "ymin": 166, "xmax": 640, "ymax": 357, "xmin_c": 0.92571, "ymin_c": 0.46142, "xmax_c": 1.0, "ymax_c": 0.99309, "class_id": "1", "image_time": "2023-11-01 03:24:00.643918", "incident_status": true, "human": 0.0}], "incident_count": 1}