{"document_id": "2bbc9c02-d0c1-4c4c-9d72-2db924851ce8", "image": {"name": "4_2023_11_04_07_26_26_633064.jpg", "height": 360, "width": 640, "storage": {}}, "usecase": {"usecase_id": 3, "name": "PathwayUsecase", "incident": [{"incident_no": 0, "incident_id": 2, "name": "Pathway Violation", "track_id": 3, "coordinate": {"x1": 225, "x2": 259, "y1": 111, "y2": 196}, "misc": [{"data": 115.81, "text": "PathwayComputation"}]}, {"incident_no": 1, "incident_id": 2, "name": "Pathway Violation", "track_id": 4, "coordinate": {"x1": 269, "x2": 291, "y1": 76, "y2": 135}, "misc": [{"data": 125.45, "text": "PathwayComputation"}]}, {"incident_no": 2, "incident_id": 2, "name": "Pathway Violation", "track_id": 21, "coordinate": {"x1": 428, "x2": 454, "y1": 98, "y2": 133}, "misc": [{"data": 138.46, "text": "PathwayComputation"}]}]}, "time": {"timestamp": 1699082786000, "zone": "", "incident_time": "2023-11-04 07:26:26.633064", "UTC_time": "2023-11-04 07:26:26.633064"}, "hierarchy": {"camera_id": 4, "camera_name": "CAM_PANTRY_01", "subsite_id": 4, "subsite_name": "Floor 5", "location_id": 4, "location_name": "Office", "customer_id": 2, "customer_name": "Tata iQ", "zone_id": 4, "zone_name": "Pantry", "city_name": "Bangalore", "city_id": 4}, "pipeline_inform": {"preprocess_id": 2, "schedule_id": "", "camera_group_id": 17, "model_meta": [], "computation_meta": []}, "prediction": [{"class": 0, "id": 3, "class_name": "human", "score": 0.88, "xmin": 225, "ymin": 111, "xmax": 259, "ymax": 196, "xmin_c": 0.35186, "ymin_c": 0.30902, "xmax_c": 0.4051, "ymax_c": 0.5459, "class_id": "1", "image_time": "2023-11-04 07:26:26.633064", "incident_status": true, "human": 115.81}, {"class": 0, "id": 4, "class_name": "human", "score": 0.79, "xmin": 269, "ymin": 76, "xmax": 291, "ymax": 135, "xmin_c": 0.42149, "ymin_c": 0.21319, "xmax_c": 0.45559, "ymax_c": 0.37594, "class_id": "1", "image_time": "2023-11-04 07:26:26.633064", "incident_status": true, "human": 125.45}, {"class": 0, "id": 21, "class_name": "human", "score": 0.2, "xmin": 428, "ymin": 98, "xmax": 454, "ymax": 133, "xmin_c": 0.6699, "ymin_c": 0.27411, "xmax_c": 0.71086, "ymax_c": 0.37017, "class_id": "1", "image_time": "2023-11-04 07:26:26.633064", "incident_status": true, "human": 138.46}], "incident_count": 3}