{"document_id": "26ded034-37d8-473a-939a-9984a7b8e04b", "image": {"name": "12_2023_11_04_14_36_25_352329.jpg", "height": 360, "width": 640, "storage": {}}, "usecase": {"usecase_id": 15, "name": "intrusion incident", "incident": [{"incident_no": 1, "incident_id": 8, "name": "intrusion", "coordinate": {"x1": 71, "x2": 121, "y1": 206, "y2": 321}, "track_id": 8, "misc": []}]}, "time": {"timestamp": 1699108585000, "zone": "", "incident_time": "2023-11-04 14:36:25.352329", "UTC_time": "2023-11-04 14:36:25.352329"}, "hierarchy": {"camera_id": 12, "camera_name": "intrusion", "subsite_id": 4, "subsite_name": "Floor 5", "location_id": 4, "location_name": "Office", "customer_id": 2, "customer_name": "Tata iQ", "zone_id": 4, "zone_name": "Pantry", "city_name": "Bangalore", "city_id": 4}, "pipeline_inform": {"preprocess_id": null, "schedule_id": "", "camera_group_id": 30, "model_meta": [], "computation_meta": []}, "prediction": [{"class": 0, "id": 7, "class_name": "human", "score": 0.81, "xmin": 144, "ymin": 153, "xmax": 177, "ymax": 255, "xmin_c": 0.22643, "ymin_c": 0.4261, "xmax_c": 0.2779, "ymax_c": 0.70902, "class_id": "1", "image_time": "2023-11-04 14:36:25.352329", "incident_status": true, "human": 340.0}, {"class": 0, "id": 8, "class_name": "human", "score": 0.71, "xmin": 71, "ymin": 206, "xmax": 121, "ymax": 321, "xmin_c": 0.11177, "ymin_c": 0.57494, "xmax_c": 0.1899, "ymax_c": 0.89274, "class_id": "1", "image_time": "2023-11-04 14:36:25.352329", "incident_status": true, "human": 333.82}, {"class": 0, "id": 23, "class_name": "human", "score": 0.26, "xmin": 593, "ymin": 76, "xmax": 640, "ymax": 356, "xmin_c": 0.92725, "ymin_c": 0.21262, "xmax_c": 1.0, "ymax_c": 0.99006, "class_id": "1", "image_time": "2023-11-04 14:36:25.352329", "incident_status": true, "human": 207.75}], "incident_count": 1}