{"document_id": "f45f938b-6072-404d-8784-e4006644507f", "image": {"name": "4_2023_11_01_11_37_20_707688.jpg", "height": 360, "width": 640, "storage": {}}, "usecase": {"usecase_id": 3, "name": "PathwayUsecase", "incident": [{"incident_no": 0, "incident_id": 2, "name": "Pathway Violation", "track_id": null, "coordinate": {"x1": 223, "x2": 285, "y1": 165, "y2": 329}, "misc": [{"data": 42.04, "text": "PathwayComputation"}]}]}, "time": {"timestamp": 1698838640000, "zone": "", "incident_time": "2023-11-01 11:37:20.707688", "UTC_time": "2023-11-01 11:37:20.707688"}, "hierarchy": {"camera_id": 4, "camera_name": "CAM_PANTRY_01", "subsite_id": 4, "subsite_name": "Floor 5", "location_id": 4, "location_name": "Office", "customer_id": 2, "customer_name": "Tata iQ", "zone_id": 4, "zone_name": "Pantry", "city_name": "Bangalore", "city_id": 4}, "pipeline_inform": {"preprocess_id": 2, "schedule_id": "", "camera_group_id": 17, "model_meta": [], "computation_meta": []}, "prediction": [{"class": 0, "id": null, "class_name": "human", "score": 0.88, "xmin": 223, "ymin": 165, "xmax": 285, "ymax": 329, "xmin_c": 0.35, "ymin_c": 0.45996, "xmax_c": 0.44669, "ymax_c": 0.91583, "class_id": "1", "image_time": "2023-11-01 11:37:20.707688", "incident_status": true, "human": 42.04}, {"class": 0, "id": null, "class_name": "human", "score": 0.86, "xmin": 405, "ymin": 125, "xmax": 445, "ymax": 260, "xmin_c": 0.63291, "ymin_c": 0.34987, "xmax_c": 0.69656, "ymax_c": 0.72372, "class_id": "1", "image_time": "2023-11-01 11:37:20.707688", "incident_status": false, "human": 0.0}, {"class": 0, "id": null, "class_name": "human", "score": 0.85, "xmin": 366, "ymin": 145, "xmax": 411, "ymax": 284, "xmin_c": 0.57298, "ymin_c": 0.40555, "xmax_c": 0.64245, "ymax_c": 0.78944, "class_id": "1", "image_time": "2023-11-01 11:37:20.707688", "incident_status": false, "human": 0.0}, {"class": 0, "id": null, "class_name": "human", "score": 0.21, "xmin": 592, "ymin": 184, "xmax": 639, "ymax": 356, "xmin_c": 0.92577, "ymin_c": 0.5119, "xmax_c": 0.99992, "ymax_c": 0.99085, "class_id": "1", "image_time": "2023-11-01 11:37:20.707688", "incident_status": false, "human": 0.0}], "incident_count": 1}