{"document_id": "ff27ec2f-64ae-4bb3-97e8-0ab50a3d5ef7", "image": {"name": "4_2023_11_01_05_37_22_362806.jpg", "height": 360, "width": 640, "storage": {}}, "usecase": {"usecase_id": 3, "name": "PathwayUsecase", "incident": [{"incident_no": 0, "incident_id": 2, "name": "Pathway Violation", "track_id": null, "coordinate": {"x1": 216, "x2": 279, "y1": 149, "y2": 302}, "misc": [{"data": 302.22, "text": "PathwayComputation"}]}, {"incident_no": 1, "incident_id": 2, "name": "Pathway Violation", "track_id": null, "coordinate": {"x1": 429, "x2": 454, "y1": 98, "y2": 134}, "misc": [{"data": 392.0, "text": "PathwayComputation"}]}]}, "time": {"timestamp": 1698817042000, "zone": "", "incident_time": "2023-11-01 05:37:22.362806", "UTC_time": "2023-11-01 05:37:22.362806"}, "hierarchy": {"camera_id": 4, "camera_name": "CAM_PANTRY_01", "subsite_id": 4, "subsite_name": "Floor 5", "location_id": 4, "location_name": "Office", "customer_id": 2, "customer_name": "Tata iQ", "zone_id": 4, "zone_name": "Pantry", "city_name": "Bangalore", "city_id": 4}, "pipeline_inform": {"preprocess_id": 2, "schedule_id": "", "camera_group_id": 17, "model_meta": [], "computation_meta": []}, "prediction": [{"class": 0, "id": null, "class_name": "human", "score": 0.9, "xmin": 216, "ymin": 149, "xmax": 279, "ymax": 302, "xmin_c": 0.33832, "ymin_c": 0.41624, "xmax_c": 0.43668, "ymax_c": 0.84001, "class_id": "1", "image_time": "2023-11-01 05:37:22.362806", "incident_status": true, "human": 302.22}, {"class": 0, "id": null, "class_name": "human", "score": 0.86, "xmin": 350, "ymin": 121, "xmax": 398, "ymax": 258, "xmin_c": 0.54739, "ymin_c": 0.33665, "xmax_c": 0.62336, "ymax_c": 0.71936, "class_id": "1", "image_time": "2023-11-01 05:37:22.362806", "incident_status": false, "human": 0.0}, {"class": 0, "id": null, "class_name": "human", "score": 0.14, "xmin": 429, "ymin": 98, "xmax": 454, "ymax": 134, "xmin_c": 0.67113, "ymin_c": 0.27498, "xmax_c": 0.71064, "ymax_c": 0.37381, "class_id": "1", "image_time": "2023-11-01 05:37:22.362806", "incident_status": true, "human": 392.0}, {"class": 0, "id": null, "class_name": "human", "score": 0.12, "xmin": 592, "ymin": 175, "xmax": 639, "ymax": 356, "xmin_c": 0.9262, "ymin_c": 0.48649, "xmax_c": 0.99995, "ymax_c": 0.98978, "class_id": "1", "image_time": "2023-11-01 05:37:22.362806", "incident_status": false, "human": 0.0}], "incident_count": 2}