{"document_id": "a4e0be7e-ac3f-4b74-9617-56852ad7ab0f", "image": {"name": "12_2023_11_03_20_36_23_347607.jpg", "height": 360, "width": 640, "storage": {}}, "usecase": {"usecase_id": 15, "name": "intrusion incident", "incident": [{"incident_no": 0, "incident_id": 8, "name": "intrusion", "coordinate": {"x1": 452, "x2": 498, "y1": 126, "y2": 233}, "track_id": null, "misc": []}, {"incident_no": 1, "incident_id": 8, "name": "intrusion", "coordinate": {"x1": 219, "x2": 253, "y1": 135, "y2": 224}, "track_id": null, "misc": []}, {"incident_no": 2, "incident_id": 8, "name": "intrusion", "coordinate": {"x1": 592, "x2": 640, "y1": 103, "y2": 357}, "track_id": null, "misc": []}]}, "time": {"timestamp": 1699043783000, "zone": "", "incident_time": "2023-11-03 20:36:23.347607", "UTC_time": "2023-11-03 20:36:23.347607"}, "hierarchy": {"camera_id": 12, "camera_name": "intrusion", "subsite_id": 4, "subsite_name": "Floor 5", "location_id": 4, "location_name": "Office", "customer_id": 2, "customer_name": "Tata iQ", "zone_id": 4, "zone_name": "Pantry", "city_name": "Bangalore", "city_id": 4}, "pipeline_inform": {"preprocess_id": null, "schedule_id": "", "camera_group_id": 30, "model_meta": [], "computation_meta": []}, "prediction": [{"class": 0, "id": null, "class_name": "human", "score": 0.83, "xmin": 452, "ymin": 126, "xmax": 498, "ymax": 233, "xmin_c": 0.70688, "ymin_c": 0.35111, "xmax_c": 0.77897, "ymax_c": 0.6482, "class_id": "1", "image_time": "2023-11-03 20:36:23.347607", "incident_status": true, "human": 112.39}, {"class": 0, "id": null, "class_name": "human", "score": 0.79, "xmin": 219, "ymin": 135, "xmax": 253, "ymax": 224, "xmin_c": 0.34222, "ymin_c": 0.37706, "xmax_c": 0.39537, "ymax_c": 0.62494, "class_id": "1", "image_time": "2023-11-03 20:36:23.347607", "incident_status": true, "human": 115.81}, {"class": 0, "id": null, "class_name": "human", "score": 0.27, "xmin": 592, "ymin": 103, "xmax": 640, "ymax": 357, "xmin_c": 0.92625, "ymin_c": 0.28889, "xmax_c": 1.0, "ymax_c": 0.99316, "class_id": "1", "image_time": "2023-11-03 20:36:23.347607", "incident_status": true, "human": 0.0}], "incident_count": 3}